rshell/__init__.py
rshell/command_line.py
rshell/dfutils.py
rshell/getch.py
rshell/main.py
rshell/pyboard.py
rshell/version.py
rshell_python3_12-0.0.36.dist-info/licenses/LICENSE
tests/hello.py
tests/make_all_bytes.py
tests/tree_cmp.py
rshell_python3_12-0.0.36.dist-info/METADATA
rshell_python3_12-0.0.36.dist-info/WHEEL
rshell_python3_12-0.0.36.dist-info/entry_points.txt
rshell_python3_12-0.0.36.dist-info/top_level.txt
rshell_python3_12-0.0.36.dist-info/RECORD
