Metadata-Version: 2.4
Name: rshell-python3.12
Version: 0.0.36
Summary: A remote shell for working with MicroPython boards. UPDATED: To work with Python 3.12
Home-page: https://github.com/avabellaw/rshell-python3.12
Author: Dave Hylands
Author-email: dhylands@gmail.com
License: MIT
Keywords: micropython shell
Classifier: Development Status :: 3 - Alpha
Classifier: Environment :: Console
Classifier: Intended Audience :: Developers
Classifier: License :: OSI Approved :: MIT License
Classifier: Natural Language :: English
Classifier: Operating System :: POSIX :: Linux
Classifier: Programming Language :: Python
Classifier: Programming Language :: Python :: 3
Classifier: Topic :: Software Development :: Embedded Systems
Classifier: Topic :: System :: Shells
Classifier: Topic :: Terminals :: Serial
Classifier: Topic :: Utilities
License-File: LICENSE
Requires-Dist: pyserial
Requires-Dist: pyudev>=0.16
Requires-Dist: pyreadline3; sys_platform == "win32"
Dynamic: author
Dynamic: author-email
Dynamic: classifier
Dynamic: description
Dynamic: home-page
Dynamic: keywords
Dynamic: license
Dynamic: license-file
Dynamic: provides-extra
Dynamic: requires-dist
Dynamic: summary
